{
  "total_population": 2,
  "average_population_per_cell": 2.0,
  "max_population_cell": 2,
  "min_population_cell": 2,
  "population_std": NaN,
  "population_density_km2": 2.5464790894703255,
  "closest_population_distance": 449.10021432967807,
  "average_population_distance": 449.10021432967807,
  "farthest_population_distance": 449.10021432967807,
  "population_within_100m": 0,
  "density_within_100m": 0.0,
  "population_within_250m": 0,
  "density_within_250m": 0.0,
  "population_within_500m": 2,
  "density_within_500m": 2.5464790894703255,
  "population_gini": 0.0,
  "population_entropy": 0.0,
  "population_center_distance": 0.0,
  "populated_cells_count": 1,
  "empty_cells_ratio": 0.0
}