[
  {
    "feature_type": "atms",
    "lat": 46.9456416,
    "lon": 7.3744145,
    "tags": {
      "amenity": "atm",
      "brand": "Migros Bank",
      "cash_in": "yes",
      "level": "1",
      "level:ref": "0",
      "operator": "Migros Bank AG"
    },
    "distance_to_station": 367.08608989420827
  },
  {
    "feature_type": "atms",
    "lat": 46.945659,
    "lon": 7.3744172,
    "tags": {
      "amenity": "atm",
      "brand": "Migros Bank",
      "level": "1",
      "level:ref": "0",
      "operator": "Migros Bank AG"
    },
    "distance_to_station": 367.2432802899889
  },
  {
    "feature_type": "atms",
    "lat": 46.9454755,
    "lon": 7.3737759,
    "tags": {
      "amenity": "atm",
      "operator": "PostFinance",
      "operator:wikidata": "Q449233"
    },
    "distance_to_station": 412.2582296425724
  },
  {
    "feature_type": "atms",
    "lat": 46.944304,
    "lon": 7.3734568,
    "tags": {
      "amenity": "atm",
      "cash_in": "no",
      "indoor": "yes",
      "operator": "Migros Bank"
    },
    "distance_to_station": 441.22745405927594
  }
]