[
  {
    "feature_type": "cafes",
    "lat": 46.9451172,
    "lon": 7.4269599,
    "tags": {
      "alt_name": "Ferdinand Coffee",
      "amenity": "cafe",
      "cuisine": "coffee_shop",
      "name": "Ferdinandcoffee To Go",
      "opening_hours": "Tu-Fr 07:00-15:00",
      "takeaway": "only",
      "website": "https://ferdinand-coffee.ch/pages/ferdinandcoffee-to-go"
    },
    "distance_to_station": 170.14598016199068
  },
  {
    "feature_type": "cafes",
    "lat": 46.9417947,
    "lon": 7.4312629,
    "tags": {
      "amenity": "cafe",
      "check_date": "2025-05-26",
      "check_date:opening_hours": "2025-05-26",
      "internet_access": "wlan",
      "internet_access:fee": "customers",
      "name": "Drip Roasters",
      "opening_hours": "Mo-Fr 08:00-18:00; Sa,Su 09:00-17:00",
      "operator": "Drip Coffee GmbH",
      "start_date": "2020-03-06",
      "website": "https://www.driproasters.ch/de/l/cafe"
    },
    "distance_to_station": 354.30255326183624
  },
  {
    "feature_type": "cafes",
    "lat": 46.9468015,
    "lon": 7.4345281,
    "tags": {
      "alt_name": "Caf\u00e9-Bar City West",
      "amenity": "cafe",
      "level": "2",
      "name": "City West"
    },
    "distance_to_station": 480.49381686999266
  }
]